tap_formbricks/__init__.py
tap_formbricks/__main__.py
tap_formbricks/client.py
tap_formbricks/streams.py
tap_formbricks/tap.py
tap_formbricks-0.0.3.dist-info/LICENSE
tap_formbricks-0.0.3.dist-info/METADATA
tap_formbricks-0.0.3.dist-info/WHEEL
tap_formbricks-0.0.3.dist-info/entry_points.txt
tap_formbricks-0.0.3.dist-info/RECORD
